rsDrawioUtils/__init__.py
rsDrawioUtils/drawioPy.py
rsDrawioUtils-1.1.0.dist-info/LICENSE
rsDrawioUtils-1.1.0.dist-info/METADATA
rsDrawioUtils-1.1.0.dist-info/WHEEL
rsDrawioUtils-1.1.0.dist-info/entry_points.txt
rsDrawioUtils-1.1.0.dist-info/top_level.txt
rsDrawioUtils-1.1.0.dist-info/RECORD
